openapi_client/__init__.py
openapi_client/api_client.py
openapi_client/configuration.py
openapi_client/exceptions.py
openapi_client/model_utils.py
openapi_client/rest.py
openapi_client/api/__init__.py
openapi_client/api/authentication_api.py
openapi_client/api/sdwan_device_policy_api.py
openapi_client/api/sdwan_device_template_api.py
openapi_client/api/sdwan_fabric_devices_api.py
openapi_client/apis/__init__.py
openapi_client/model/__init__.py
openapi_client/models/__init__.py
pied_piper_openapi_client-1.0.4.dist-info/METADATA
pied_piper_openapi_client-1.0.4.dist-info/WHEEL
pied_piper_openapi_client-1.0.4.dist-info/top_level.txt
pied_piper_openapi_client-1.0.4.dist-info/RECORD
