Metadata-Version: 2.1
Name: pied-piper-openapi-client
Version: 1.0.4
Summary: Cisco-Reservable-SD-WAN
Home-page: 
Author: OpenAPI Generator community
Author-email: team@openapitools.org
Keywords: OpenAPI,OpenAPI-Generator,Cisco-Reservable-SD-WAN
Requires-Python: >=3.6
Requires-Dist: urllib3 (>=1.25.3)
Requires-Dist: python-dateutil
